pyTRADE/__init__.py
pyTRADE/core/__init__.py
pyTRADE/core/java_util.py
pyTRADE/core/trade.properties
pyTRADE/core/wrapper.py
pyTRADE/core/jars/__init__.py
pyTRADE/core/jars/commons-lang3-3.8.1.jar
pyTRADE/core/jars/javax.annotation-api-1.3.2.jar
pyTRADE/core/jars/slf4j-api-2.0.13.jar
pyTRADE/core/jars/trade-1.1.1.jar
pyTRADE/core/jars/vecmath-1.5.2.jar
pyTRADE/examples/__init__.py
pyTRADE/examples/minimal_example.py
pyTRADE/examples/rl_example.py
pyTRADE/examples/robosuite_example.py
pytrade_wrapper-1.1.0.dist-info/METADATA
pytrade_wrapper-1.1.0.dist-info/WHEEL
pytrade_wrapper-1.1.0.dist-info/RECORD
