Metadata-Version: 2.3
Name: pyTRADE-wrapper
Version: 1.1.0
Summary: A jpype based wrapper for using TRADE with Python
Author-email: Marlow Fawn <marlow.fawn@tufts.edu>
Requires-Python: >=3.10
Requires-Dist: jpype1==1.5.0
Requires-Dist: numpy==2.0.2
